README.md
setup.py
src/overcooked_ai.egg-info/PKG-INFO
src/overcooked_ai.egg-info/SOURCES.txt
src/overcooked_ai.egg-info/dependency_links.txt
src/overcooked_ai.egg-info/requires.txt
src/overcooked_ai.egg-info/top_level.txt
src/overcooked_ai_py/__init__.py
src/overcooked_ai_py/static.py
src/overcooked_ai_py/utils.py
src/overcooked_ai_py/agents/__init__.py
src/overcooked_ai_py/agents/agent.py
src/overcooked_ai_py/agents/benchmarking.py
src/overcooked_ai_py/data/fonts/Roboto-Regular.ttf
src/overcooked_ai_py/data/graphics/arrow.png
src/overcooked_ai_py/data/graphics/chefs.json
src/overcooked_ai_py/data/graphics/chefs.png
src/overcooked_ai_py/data/graphics/interact.png
src/overcooked_ai_py/data/graphics/objects.json
src/overcooked_ai_py/data/graphics/objects.png
src/overcooked_ai_py/data/graphics/soups.json
src/overcooked_ai_py/data/graphics/soups.png
src/overcooked_ai_py/data/graphics/stay.png
src/overcooked_ai_py/data/graphics/terrain.json
src/overcooked_ai_py/data/graphics/terrain.png
src/overcooked_ai_py/data/human_data/clean_test_trials.pickle
src/overcooked_ai_py/data/human_data/clean_train_trials.pickle
src/overcooked_ai_py/data/layouts/asymmetric_advantages.layout
src/overcooked_ai_py/data/layouts/asymmetric_advantages_tomato.layout
src/overcooked_ai_py/data/layouts/bonus_order_test.layout
src/overcooked_ai_py/data/layouts/bottleneck.layout
src/overcooked_ai_py/data/layouts/centre_objects.layout
src/overcooked_ai_py/data/layouts/centre_pots.layout
src/overcooked_ai_py/data/layouts/coordination_ring.layout
src/overcooked_ai_py/data/layouts/corridor.layout
src/overcooked_ai_py/data/layouts/counter_circuit.layout
src/overcooked_ai_py/data/layouts/counter_circuit_o_1order.layout
src/overcooked_ai_py/data/layouts/cramped_corridor.layout
src/overcooked_ai_py/data/layouts/cramped_room.layout
src/overcooked_ai_py/data/layouts/cramped_room_o_3orders.layout
src/overcooked_ai_py/data/layouts/cramped_room_single.layout
src/overcooked_ai_py/data/layouts/cramped_room_tomato.layout
src/overcooked_ai_py/data/layouts/five_by_five.layout
src/overcooked_ai_py/data/layouts/forced_coordination.layout
src/overcooked_ai_py/data/layouts/forced_coordination_tomato.layout
