Metadata-Version: 2.1
Name: overcooked-ai
Version: 1.1.0
Summary: Cooperative multi-agent environment based on Overcooked
Home-page: https://github.com/HumanCompatibleAI/overcooked_ai
Author: Nathan Miller
Author-email: nathan_miller23@berkeley.edu
License: UNKNOWN
Download-URL: https://github.com/HumanCompatibleAI/overcooked_ai/archive/refs/tags/1.1.0.tar.gz
Keywords: Overcooked,AI,Reinforcement Learning
Platform: UNKNOWN
